README
setup.py
test/test_compile.py
test/test_socket.py
tiddlywebplugins/__init__.py
tiddlywebplugins.twikified.egg-info/PKG-INFO
tiddlywebplugins.twikified.egg-info/SOURCES.txt
tiddlywebplugins.twikified.egg-info/dependency_links.txt
tiddlywebplugins.twikified.egg-info/namespace_packages.txt
tiddlywebplugins.twikified.egg-info/not-zip-safe
tiddlywebplugins.twikified.egg-info/requires.txt
tiddlywebplugins.twikified.egg-info/top_level.txt
tiddlywebplugins/twikified/__init__.py
tiddlywebplugins/twikified/render.py