Metadata-Version: 1.0
Name: tiddlywebplugins.twikified
Version: 0.1.1
Summary: Interface between TiddlyWeb and the node.js wikifier for TiddlyWiki text
Home-page: http://pypi.python.org/pypi/tiddlywebplugins.twikified
Author: Ben Paddock
Author-email: pads@thisispads.me.uk
License: UNKNOWN
Platform: Posix; MacOS X; Windows
